juffi/__init__.py
juffi/__main__.py
juffi/input_controller.py
juffi/output_controller.py
juffi/helpers/__init__.py
juffi/helpers/curses_utils.py
juffi/helpers/datetime_parser.py
juffi/helpers/dev_utils.py
juffi/helpers/indexed_dict.py
juffi/helpers/list_utils.py
juffi/helpers/state.py
juffi/models/__init__.py
juffi/models/column.py
juffi/models/juffi_model.py
juffi/models/log_entry.py
juffi/viewmodels/__init__.py
juffi/viewmodels/app.py
juffi/viewmodels/browse.py
juffi/viewmodels/column_management.py
juffi/viewmodels/details.py
juffi/viewmodels/entries.py
juffi/viewmodels/help.py
juffi/views/__init__.py
juffi/views/app.py
juffi/views/browse.py
juffi/views/column_management.py
juffi/views/details.py
juffi/views/entries.py
juffi/views/help.py
juffi-0.4.0.dist-info/licenses/LICENSE
juffi-0.4.0.dist-info/METADATA
juffi-0.4.0.dist-info/WHEEL
juffi-0.4.0.dist-info/entry_points.txt
juffi-0.4.0.dist-info/top_level.txt
juffi-0.4.0.dist-info/RECORD
